{"count": 2, "data": [{"totalViews": 880, "date": "2018-08-29", "pageAmount": 10, "pageData": [{"pageName": "Home", "views": 327}, {"pageName": "Team", "views": 103}, {"pageName": "Description", "views": 101}, {"pageName": "Collaborations", "views": 60}, {"pageName": "Attributions", "views": 57}, {"pageName": "Design", "views": 47}, {"pageName": "Parts", "views": 47}, {"pageName": "Experiments", "views": 46}, {"pageName": "InterLab", "views": 46}, {"pageName": "team team members.html", "views": 46}]}, {"totalViews": 884, "date": "2018-08-30", "pageAmount": 10, "pageData": [{"pageName": "Home", "views": 330}, {"pageName": "Team", "views": 104}, {"pageName": "Description", "views": 101}, {"pageName": "Collaborations", "views": 60}, {"pageName": "Attributions", "views": 57}, {"pageName": "Design", "views": 47}, {"pageName": "Parts", "views": 47}, {"pageName": "Experiments", "views": 46}, {"pageName": "InterLab", "views": 46}, {"pageName": "team team members.html", "views": 46}]}], "teamName": "Austin LASA"}