{"count": 2, "data": [{"totalViews": 8332, "date": "2018-08-29", "pageAmount": 39, "pageData": [{"pageName": "Home", "views": 1713}, {"pageName": "Description", "views": 762}, {"pageName": "Team", "views": 719}, {"pageName": "Game", "views": 443}, {"pageName": "NavBarCSS", "views": 284}, {"pageName": "NavBar", "views": 281}, {"pageName": "Notebook", "views": 248}, {"pageName": "Design", "views": 233}, {"pageName": "Quiz", "views": 227}, {"pageName": "Navpage", "views": 214}, {"pageName": "Human Practices", "views": 213}, {"pageName": "Experiments", "views": 205}, {"pageName": "Collaborations", "views": 178}, {"pageName": "Footer", "views": 178}, {"pageName": "MeetTheTeam", "views": 171}, {"pageName": "Safety", "views": 169}, {"pageName": "Parts", "views": 157}, {"pageName": "Model", "views": 145}, {"pageName": "Genetic Pathway", "views": 126}, {"pageName": "Demonstrate", "views": 116}, {"pageName": "Public Engagement", "views": 116}, {"pageName": "Interlab", "views": 115}, {"pageName": "Applied Design", "views": 105}, {"pageName": "Acknowledgement", "views": 104}, {"pageName": "Hardware", "views": 102}, {"pageName": "History", "views": 100}, {"pageName": "Entrepreneurship", "views": 99}, {"pageName": "Results", "views": 95}, {"pageName": "Composite Part", "views": 87}, {"pageName": "InterLab", "views": 87}, {"pageName": "Part Collection", "views": 77}, {"pageName": "Basic Part", "views": 72}, {"pageName": "Attributions", "views": 71}, {"pageName": "Applied Model", "views": 56}, {"pageName": "Improve", "views": 56}, {"pageName": "Protocols", "views": 56}, {"pageName": "Plant", "views": 51}, {"pageName": "Software", "views": 51}, {"pageName": "Measurement", "views": 50}]}, {"totalViews": 8364, "date": "2018-08-30", "pageAmount": 39, "pageData": [{"pageName": "Home", "views": 1720}, {"pageName": "Description", "views": 764}, {"pageName": "Team", "views": 720}, {"pageName": "Game", "views": 443}, {"pageName": "NavBarCSS", "views": 285}, {"pageName": "NavBar", "views": 281}, {"pageName": "Notebook", "views": 249}, {"pageName": "Design", "views": 234}, {"pageName": "Quiz", "views": 228}, {"pageName": "Navpage", "views": 216}, {"pageName": "Human Practices", "views": 214}, {"pageName": "Experiments", "views": 206}, {"pageName": "Collaborations", "views": 178}, {"pageName": "Footer", "views": 178}, {"pageName": "MeetTheTeam", "views": 171}, {"pageName": "Safety", "views": 170}, {"pageName": "Parts", "views": 158}, {"pageName": "Model", "views": 147}, {"pageName": "Genetic Pathway", "views": 126}, {"pageName": "Demonstrate", "views": 116}, {"pageName": "Interlab", "views": 116}, {"pageName": "Public Engagement", "views": 116}, {"pageName": "Acknowledgement", "views": 106}, {"pageName": "Applied Design", "views": 105}, {"pageName": "Hardware", "views": 103}, {"pageName": "History", "views": 102}, {"pageName": "Entrepreneurship", "views": 99}, {"pageName": "Results", "views": 95}, {"pageName": "Composite Part", "views": 88}, {"pageName": "InterLab", "views": 87}, {"pageName": "Part Collection", "views": 77}, {"pageName": "Basic Part", "views": 73}, {"pageName": "Attributions", "views": 71}, {"pageName": "Improve", "views": 57}, {"pageName": "Applied Model", "views": 56}, {"pageName": "Protocols", "views": 56}, {"pageName": "Software", "views": 52}, {"pageName": "Plant", "views": 51}, {"pageName": "Measurement", "views": 50}]}], "teamName": "Purdue"}