{"count": 2, "data": [{"totalViews": 4378, "date": "2018-08-29", "pageAmount": 12, "pageData": [{"pageName": "Home", "views": 1502}, {"pageName": "sandbox", "views": 1080}, {"pageName": "Templates", "views": 631}, {"pageName": "Team", "views": 387}, {"pageName": "InterLab", "views": 247}, {"pageName": "sandboxDavid", "views": 140}, {"pageName": "Templates", "views": 104}, {"pageName": "Notebook", "views": 76}, {"pageName": "Description", "views": 64}, {"pageName": "Human Practices", "views": 53}, {"pageName": "Safety", "views": 49}, {"pageName": "CSS", "views": 45}]}, {"totalViews": 4391, "date": "2018-08-30", "pageAmount": 12, "pageData": [{"pageName": "Home", "views": 1512}, {"pageName": "sandbox", "views": 1080}, {"pageName": "Templates", "views": 631}, {"pageName": "Team", "views": 387}, {"pageName": "InterLab", "views": 248}, {"pageName": "sandboxDavid", "views": 140}, {"pageName": "Templates", "views": 104}, {"pageName": "Notebook", "views": 76}, {"pageName": "Description", "views": 64}, {"pageName": "Human Practices", "views": 53}, {"pageName": "Safety", "views": 50}, {"pageName": "CSS", "views": 46}]}], "teamName": "Tec-Monterrey"}